{ "_id" : ObjectId("5d48f270174f531296f408de"), "name" : "XIMENA" }
{ "_id" : ObjectId("5d48f270174f531296f408df"), "job" : "CORREDOR" }

{ "_id" : ObjectId("5d48f270174f531296f408de"), "name" : "XIMENA" }
{ "_id" : ObjectId("5d48f270174f531296f408df"), "job" : "CORREDOR" }
{ "_id" : 0, "name" : "JUANA", "last name: " : "ROMERO" }
{ "_id" : ObjectId("5d48f3cf824463773bfdb6eb") }

{ "_id" : ObjectId("5d48f270174f531296f408de"), "name" : "XIMENA" }
{ "_id" : ObjectId("5d48f270174f531296f408df"), "job" : "CORREDOR" }
{ "_id" : 0, "name" : "JUANA", "last name: " : "ROMERO" }
{ "_id" : ObjectId("5d48f3cf824463773bfdb6eb") }
{ "_id" : "1121968569", "Name" : "Alejandro", "lastName" : "Sacristan" }
{ "_id" : "51811259", "Name" : "Iris", "lastName" : "Leal" }

{ "_id" : ObjectId("5d48f270174f531296f408de"), "name" : "XIMENA" }
{ "_id" : ObjectId("5d48f270174f531296f408df"), "job" : "CORREDOR" }
{ "_id" : 0, "name" : "JUANA", "last name: " : "ROMERO" }
{ "_id" : ObjectId("5d48f3cf824463773bfdb6eb") }
{ "_id" : "1121968569", "Name" : "Alejandro", "lastName" : "Sacristan" }
{ "_id" : "51811259", "Name" : "Iris", "lastName" : "Leal" }
{ "_id" : "0", "Name" : "ll", "lastName" : "dd" }
{ "_id" : "99", "Name" : "ll", "lastName" : "dd" }
{ "_id" : "1121968369", "Name" : "Ximena", "lastName" : "Corredor Gaitán" }
{ "_id" : "9090", "Name" : "ijij", "lastName" : "kook" }

{ "_id" : ObjectId("5d48f270174f531296f408de"), "name" : "XIMENA" }
{ "_id" : ObjectId("5d48f270174f531296f408df"), "job" : "CORREDOR" }
{ "_id" : 0, "name" : "JUANA", "last name: " : "ROMERO" }
{ "_id" : ObjectId("5d48f3cf824463773bfdb6eb") }
{ "_id" : "1121968569", "Name" : "Alejandro", "lastName" : "Sacristan" }
{ "_id" : "51811259", "Name" : "Iris", "lastName" : "Leal" }
{ "_id" : "0", "Name" : "ll", "lastName" : "dd" }
{ "_id" : "99", "Name" : "ll", "lastName" : "dd" }
{ "_id" : "1121968369", "Name" : "Ximena", "lastName" : "Corredor Gaitán" }
{ "_id" : "9090", "Name" : "ijij", "lastName" : "kook" }
{ "_id" : "1121", "Name" : "III", "lastName" : "OOO" }
{ "_id" : "222", "Name" : "KKK", "lastName" : "LLL" }
{ "_id" : "111", "Name" : "ppp", "lastName" : "hhh" }
{ "_id" : "999", "Name" : "lll", "lastName" : "jjj" }

{ "_id" : ObjectId("5d48f270174f531296f408de"), "name" : "XIMENA" }
{ "_id" : ObjectId("5d48f270174f531296f408df"), "job" : "CORREDOR" }
{ "_id" : 0, "name" : "JUANA", "last name: " : "ROMERO" }
{ "_id" : ObjectId("5d48f3cf824463773bfdb6eb") }
{ "_id" : "1121968569", "Name" : "Alejandro", "lastName" : "Sacristan" }
{ "_id" : "51811259", "Name" : "Iris", "lastName" : "Leal" }
{ "_id" : "0", "Name" : "ll", "lastName" : "dd" }
{ "_id" : "99", "Name" : "ll", "lastName" : "dd" }
{ "_id" : "1121968369", "Name" : "Ximena", "lastName" : "Corredor Gaitán" }
{ "_id" : "9090", "Name" : "ijij", "lastName" : "kook" }
{ "_id" : "1121", "Name" : "III", "lastName" : "OOO" }
{ "_id" : "222", "Name" : "KKK", "lastName" : "LLL" }
{ "_id" : "111", "Name" : "ppp", "lastName" : "hhh" }
{ "_id" : "999", "Name" : "lll", "lastName" : "jjj" }
{ "_id" : "1121999", "Name" : "aton", "lastName" : "ki" }
{ "_id" : "1234", "Name" : "ki", "lastName" : "aton" }

{ "_id" : ObjectId("5d48f270174f531296f408de"), "name" : "XIMENA" }
{ "_id" : ObjectId("5d48f270174f531296f408df"), "job" : "CORREDOR" }
{ "_id" : 0, "name" : "JUANA", "last name: " : "ROMERO" }
{ "_id" : ObjectId("5d48f3cf824463773bfdb6eb") }
{ "_id" : "1121968569", "Name" : "Alejandro", "lastName" : "Sacristan" }
{ "_id" : "51811259", "Name" : "Iris", "lastName" : "Leal" }
{ "_id" : "0", "Name" : "ll", "lastName" : "dd" }
{ "_id" : "99", "Name" : "ll", "lastName" : "dd" }
{ "_id" : "1121968369", "Name" : "Ximena", "lastName" : "Corredor Gaitán" }
{ "_id" : "9090", "Name" : "ijij", "lastName" : "kook" }
{ "_id" : "1121", "Name" : "III", "lastName" : "OOO" }
{ "_id" : "222", "Name" : "KKK", "lastName" : "LLL" }
{ "_id" : "111", "Name" : "ppp", "lastName" : "hhh" }
{ "_id" : "999", "Name" : "lll", "lastName" : "jjj" }
{ "_id" : "1121999", "Name" : "aton", "lastName" : "ki" }
{ "_id" : "1234", "Name" : "ki", "lastName" : "aton" }
{ "_id" : "5555", "Name" : "RRRR", "lastName" : "FFFF" }
{ "_id" : "4553", "Name" : "juju", "lastName" : "kljl" }
{ "_id" : "7777", "Name" : "iiii", "lastName" : "jjj" }
{ "_id" : 999999900, "Name" : "ooo", "lastName" : "eeeee", "Edad" : 19, "Sexo" : "M" }

{ "_id" : ObjectId("5d48f270174f531296f408de"), "name" : "XIMENA" }
{ "_id" : ObjectId("5d48f270174f531296f408df"), "job" : "CORREDOR" }
{ "_id" : 0, "name" : "JUANA", "last name: " : "ROMERO" }
{ "_id" : ObjectId("5d48f3cf824463773bfdb6eb") }
{ "_id" : "1121968569", "Name" : "Alejandro", "lastName" : "Sacristan" }
{ "_id" : "51811259", "Name" : "Iris", "lastName" : "Leal" }
{ "_id" : "0", "Name" : "ll", "lastName" : "dd" }
{ "_id" : "99", "Name" : "ll", "lastName" : "dd" }
{ "_id" : "1121968369", "Name" : "Ximena", "lastName" : "Corredor Gaitán" }
{ "_id" : "9090", "Name" : "ijij", "lastName" : "kook" }
{ "_id" : "1121", "Name" : "III", "lastName" : "OOO" }
{ "_id" : "222", "Name" : "KKK", "lastName" : "LLL" }
{ "_id" : "111", "Name" : "ppp", "lastName" : "hhh" }
{ "_id" : "999", "Name" : "lll", "lastName" : "jjj" }
{ "_id" : "1121999", "Name" : "aton", "lastName" : "ki" }
{ "_id" : "1234", "Name" : "ki", "lastName" : "aton" }
{ "_id" : "5555", "Name" : "RRRR", "lastName" : "FFFF" }
{ "_id" : "4553", "Name" : "juju", "lastName" : "kljl" }
{ "_id" : "7777", "Name" : "iiii", "lastName" : "jjj" }
{ "_id" : 999999900, "Name" : "ooo", "lastName" : "eeeee", "Edad" : 19, "Sexo" : "M" }

{ "_id" : ObjectId("5d48f270174f531296f408de"), "name" : "XIMENA" }
{ "_id" : ObjectId("5d48f270174f531296f408df"), "job" : "CORREDOR" }
{ "_id" : 0, "name" : "JUANA", "last name: " : "ROMERO" }
{ "_id" : ObjectId("5d48f3cf824463773bfdb6eb") }
{ "_id" : "1121968569", "Name" : "Alejandro", "lastName" : "Sacristan" }
{ "_id" : "51811259", "Name" : "Iris", "lastName" : "Leal" }
{ "_id" : "0", "Name" : "ll", "lastName" : "dd" }
{ "_id" : "99", "Name" : "ll", "lastName" : "dd" }
{ "_id" : "1121968369", "Name" : "Ximena", "lastName" : "Corredor Gaitán" }
{ "_id" : "9090", "Name" : "ijij", "lastName" : "kook" }
{ "_id" : "1121", "Name" : "III", "lastName" : "OOO" }
{ "_id" : "222", "Name" : "KKK", "lastName" : "LLL" }
{ "_id" : "111", "Name" : "ppp", "lastName" : "hhh" }
{ "_id" : "999", "Name" : "lll", "lastName" : "jjj" }
{ "_id" : "1121999", "Name" : "aton", "lastName" : "ki" }
{ "_id" : "1234", "Name" : "ki", "lastName" : "aton" }
{ "_id" : "5555", "Name" : "RRRR", "lastName" : "FFFF" }
{ "_id" : "4553", "Name" : "juju", "lastName" : "kljl" }
{ "_id" : "7777", "Name" : "iiii", "lastName" : "jjj" }
{ "_id" : 999999900, "Name" : "ooo", "lastName" : "eeeee", "Edad" : 19, "Sexo" : "M" }